hero/__init__.py
hero/admin.py
hero/apps.py
hero/static/css/hero/bethany_ds.css
hero/static/css/hero/medicio_ds.css
hero/static/css/hero/medilab_ds.css
hero/static/css/hero/mentor_ds.css
hero/templates/hero/_common.html
hero/templates/hero/bethany_ds.html
hero/templates/hero/medicio_ds.html
hero/templates/hero/medilab_ds.html
hero/templates/hero/mentor_ds.html
hero/templatetags/__init__.py
hero/templatetags/hero_tags.py
django_hero_ds-1.1.0.dist-info/LICENSE
django_hero_ds-1.1.0.dist-info/METADATA
django_hero_ds-1.1.0.dist-info/WHEEL
django_hero_ds-1.1.0.dist-info/top_level.txt
django_hero_ds-1.1.0.dist-info/RECORD
